octocruncher/__init__.py
octocruncher/helper_classes.py
octocruncher/octocruncher.py
octocruncher_v3-0.1.0.dist-info/LICENSE
octocruncher_v3-0.1.0.dist-info/METADATA
octocruncher_v3-0.1.0.dist-info/WHEEL
octocruncher_v3-0.1.0.dist-info/top_level.txt
octocruncher_v3-0.1.0.dist-info/RECORD
