Metadata-Version: 2.1
Name: octocruncher-v3
Version: 0.1.0
Summary: A simple package to implement the Octopart API version 3
Home-page: https://github.com/tgross35/octocruncher-v3
Author: Trevor Gross
Author-email: tgross@intrepidcs.com
License: UNKNOWN
Platform: UNKNOWN
Classifier: Programming Language :: Python :: 3
Classifier: License :: OSI Approved :: MIT License
Classifier: Operating System :: OS Independent
Requires-Python: >=3.6
